adrest/__init__.py
adrest/admin.py
adrest/api.py
adrest/forms.py
adrest/models.py
adrest/settings.py
adrest/signals.py
adrest/templatetags.py
adrest/views.py
adrest/mixin/__init__.py
adrest/mixin/auth.py
adrest/mixin/dynamic.py
adrest/mixin/emitter.py
adrest/mixin/handler.py
adrest/mixin/parser.py
adrest/mixin/throttle.py
adrest/resources/__init__.py
adrest/resources/ga.py
adrest/resources/map.py
adrest/resources/rpc.py
adrest/templates/api/error.html
adrest/templates/api/error.json
adrest/templates/api/error.xml
adrest/templates/api/map.html
adrest/templates/api/paginator.json
adrest/templates/api/paginator.xml
adrest/templates/api/updated.json
adrest/templates/api/updated.xml
adrest/tests/__init__.py
adrest/tests/client.py
adrest/tests/utils.py
adrest/utils/__init__.py
adrest/utils/auth.py
adrest/utils/emitter.py
adrest/utils/exceptions.py
adrest/utils/mail.py
adrest/utils/meta.py
adrest/utils/paginator.py
adrest/utils/parser.py
adrest/utils/response.py
adrest/utils/serializer.py
adrest/utils/status.py
adrest/utils/throttle.py
adrest/utils/tools.py
adrest-3.3.2.dist-info/DESCRIPTION.rst
adrest-3.3.2.dist-info/METADATA
adrest-3.3.2.dist-info/metadata.json
adrest-3.3.2.dist-info/RECORD
adrest-3.3.2.dist-info/top_level.txt
adrest-3.3.2.dist-info/WHEEL
example/__init__.py
example/manage.py
example/wsgi.py
example/api/__init__.py
example/api/api.py
example/api/models.py
example/api/rpc.py
example/main/__init__.py
example/main/admin.py
example/main/models.py
example/main/urls.py
example/main/views.py
example/main/tests/__init__.py
example/main/tests/base.py
example/main/utils/__init__.py
example/main/utils/cache.py
example/main/utils/files.py
example/main/utils/models.py
example/main/utils/views.py
example/settings/__init__.py
example/settings/core.py
example/settings/development.py
example/settings/production.py
example/settings/test.py
tests/__init__.py
tests/test_adrest.py
tests/core/__init__.py
tests/core/api.py
tests/core/models.py
tests/core/urls.py
tests/core/tests/__init__.py
tests/core/tests/admin.py
tests/core/tests/api.py
tests/core/tests/auth.py
tests/core/tests/dynamic.py
