Metadata-Version: 2.0
Name: adrest
Version: 3.3.2
Summary: Adrest - Another Django REST. Simple application for quick build REST API.
Requires-Dist: django (>=1.4.3)
Requires-Dist: python-mimeparse (==0.1.4)
